pyartify/__init__.py
pyartify/dither.py
pyartify/palettes.py
pyartify/pixelate.py
pyartify/utils.py
pyartify-0.1.dist-info/METADATA
pyartify-0.1.dist-info/WHEEL
pyartify-0.1.dist-info/top_level.txt
pyartify-0.1.dist-info/RECORD
