Metadata-Version: 2.1
Name: pyartify
Version: 0.1
Summary: Convert images to pixel art using retro palettes like NES, GameBoy, Minecraft, and PICO-8.
Home-page: https://github.com/shreeya2424/pyart
Author: Shreeya Singh
Project-URL: Source, https://github.com/shreeya2424/pyart
Project-URL: Bug Tracker, https://github.com/shreeya2424/pyart/issues
Requires-Python: >=3.7
Requires-Dist: Pillow
Requires-Dist: numpy
